dnadigest/__init__.py
dnadigest/rebase.yaml
dnadigest/wiki.yaml
dnadigest-0.1.2.data/scripts/digest_dna.py
dnadigest-0.1.2.data/scripts/graphic_drawer.py
dnadigest-0.1.2.dist-info/top_level.txt
dnadigest-0.1.2.dist-info/METADATA
dnadigest-0.1.2.dist-info/DESCRIPTION.rst
dnadigest-0.1.2.dist-info/metadata.json
dnadigest-0.1.2.dist-info/WHEEL
dnadigest-0.1.2.dist-info/RECORD
