Metadata-Version: 2.0
Name: dnadigest
Version: 0.1.2
Summary: Library+Tool to run restriction digests of DNA sequences
Home-page: https://github.com/erasche/restriction-digest/
Author: Stephen Crosby
Author-email: stcrosby@gmail.com
License: GPLv3
Platform: UNKNOWN
Classifier: Development Status :: 4 - Beta
Classifier: Programming Language :: Python :: 2.7
Classifier: Topic :: Scientific/Engineering :: Bio-Informatics
Requires-Dist: beautifulsoup4
Requires-Dist: pyyaml
Requires-Dist: biopython
Requires-Dist: svgwrite
